dramaprint/__init__.py
dramaprint-1.0.1.dist-info/licenses/LICENSE
dramaprint-1.0.1.dist-info/METADATA
dramaprint-1.0.1.dist-info/WHEEL
dramaprint-1.0.1.dist-info/top_level.txt
dramaprint-1.0.1.dist-info/RECORD
