Metadata-Version: 2.4
Name: dramaprint
Version: 1.0.1
Summary: Printing module with pausing and sound effects
Home-page: https://github.com/Dji-Mini-4/dramaprint
Author: Jayden Liu
License: MIT License
Requires-Python: >=3.7
License-File: LICENSE
Requires-Dist: pygame>=2.1.0
Dynamic: home-page
Dynamic: license-file
